LICENSE
MANIFEST.in
setup.py
pocket_change/__init__.py
pocket_change/auth.py
pocket_change/database.py
pocket_change/jira_lib.py
pocket_change.egg-info/PKG-INFO
pocket_change.egg-info/SOURCES.txt
pocket_change.egg-info/dependency_links.txt
pocket_change.egg-info/requires.txt
pocket_change.egg-info/top_level.txt
pocket_change/rest/__init__.py
pocket_change/rest/util.py
pocket_change/rest/components/__init__.py
pocket_change/rest/components/auth.py
pocket_change/rest/components/case.py
pocket_change/rest/components/case_execution.py
pocket_change/rest/components/jira_extensions.py
pocket_change/rest/components/test_cycle.py
pocket_change/static/case_execution_details.css
pocket_change/static/cycle_case_rollup.css
pocket_change/static/cycle_listing.css
pocket_change/static/filters.js
pocket_change/ui/__init__.py
pocket_change/ui/jira_extensions.py
pocket_change/ui/templates/case_execution_details.html
pocket_change/ui/templates/cycle_case_rollup.html
pocket_change/ui/templates/cycle_listing.html
pocket_change/ui/templates/jira_linking.html
pocket_change/ui/templates/login.html
pocket_change/ui/views/__init__.py
pocket_change/ui/views/case_execution_details.py
pocket_change/ui/views/cycle_case_rollup.py
pocket_change/ui/views/cycle_listing.py
pocket_change/ui/views/jira_linking.py
pocket_change/ui/views/login.py