Metadata-Version: 1.1
Name: pocket-change
Version: 0.0.6
Summary: The web front end for Sneeze and Pocket
Home-page: http://pocket-change.readthedocs.org/
Author: Silas Ray
Author-email: silas.ray@nytimes.com
License: Apache2.0
Platform: UNKNOWN
Classifier: Development Status :: 4 - Beta
Classifier: Intended Audience :: Information Technology
Classifier: Topic :: Software Development :: Quality Assurance
Classifier: Topic :: Software Development :: Testing
